tango_voting-0.4.1.dist-info/METADATA
tango_voting-0.4.1.dist-info/RECORD
tango_voting-0.4.1.dist-info/WHEEL
tango_voting-0.4.1.dist-info/top_level.txt
voting/__init__.py
voting/admin.py
voting/managers.py
voting/models.py
voting/views.py
voting/templates/voting/confirm_vote.html
voting/templatetags/__init__.py
voting/templatetags/voting_tags.py
voting/tests/__init__.py
voting/tests/models.py
voting/tests/runtests.py
voting/tests/settings.py
voting/tests/tests.py
